shifts/__init__.py
shifts/generate_calendar_file.py
shifts/main.py
shifts/shift.py
shifts-0.2.4.dist-info/LICENSE
shifts-0.2.4.dist-info/METADATA
shifts-0.2.4.dist-info/WHEEL
shifts-0.2.4.dist-info/entry_points.txt
shifts-0.2.4.dist-info/RECORD
